odoo/addons/l10n_es_aeat_mod303/README.rst
odoo/addons/l10n_es_aeat_mod303/__init__.py
odoo/addons/l10n_es_aeat_mod303/__manifest__.py
odoo/addons/l10n_es_aeat_mod303/data/l10n.es.aeat.mod303.report.activity.code.csv
odoo/addons/l10n_es_aeat_mod303/data/2022/aeat.model.export.config.csv
odoo/addons/l10n_es_aeat_mod303/data/2022/aeat.model.export.config.line.csv
odoo/addons/l10n_es_aeat_mod303/data/2023/aeat.model.export.config.csv
odoo/addons/l10n_es_aeat_mod303/data/2023/aeat.model.export.config.line.csv
odoo/addons/l10n_es_aeat_mod303/data/2023/l10n.es.aeat.map.tax.csv
odoo/addons/l10n_es_aeat_mod303/data/2023/l10n.es.aeat.map.tax.line.account.csv
odoo/addons/l10n_es_aeat_mod303/data/2023/l10n.es.aeat.map.tax.line.csv
odoo/addons/l10n_es_aeat_mod303/data/2023/l10n.es.aeat.map.tax.line.tax.csv
odoo/addons/l10n_es_aeat_mod303/data/2024-10/aeat.model.export.config.csv
odoo/addons/l10n_es_aeat_mod303/data/2024-10/aeat.model.export.config.line.csv
odoo/addons/l10n_es_aeat_mod303/data/2024-10/l10n.es.aeat.map.tax.csv
odoo/addons/l10n_es_aeat_mod303/data/2024-10/l10n.es.aeat.map.tax.line.csv
odoo/addons/l10n_es_aeat_mod303/data/2024-10/l10n.es.aeat.map.tax.line.tax.csv
odoo/addons/l10n_es_aeat_mod303/docs/DR303e23.xlsx
odoo/addons/l10n_es_aeat_mod303/docs/DR303e24v200.xlsx
odoo/addons/l10n_es_aeat_mod303/docs/DR303e25v101.xlsx
odoo/addons/l10n_es_aeat_mod303/i18n/bg.po
odoo/addons/l10n_es_aeat_mod303/i18n/ca.po
odoo/addons/l10n_es_aeat_mod303/i18n/cs.po
odoo/addons/l10n_es_aeat_mod303/i18n/de.po
odoo/addons/l10n_es_aeat_mod303/i18n/es.po
odoo/addons/l10n_es_aeat_mod303/i18n/es_CO.po
odoo/addons/l10n_es_aeat_mod303/i18n/es_CR.po
odoo/addons/l10n_es_aeat_mod303/i18n/eu.po
odoo/addons/l10n_es_aeat_mod303/i18n/fr.po
odoo/addons/l10n_es_aeat_mod303/i18n/gl.po
odoo/addons/l10n_es_aeat_mod303/i18n/hr.po
odoo/addons/l10n_es_aeat_mod303/i18n/l10n_es_aeat_mod303.pot
odoo/addons/l10n_es_aeat_mod303/i18n/nl.po
odoo/addons/l10n_es_aeat_mod303/i18n/pl.po
odoo_addon_l10n_es_aeat_mod303-18.0.1.0.4.dist-info/METADATA
odoo_addon_l10n_es_aeat_mod303-18.0.1.0.4.dist-info/WHEEL
odoo_addon_l10n_es_aeat_mod303-18.0.1.0.4.dist-info/top_level.txt
odoo_addon_l10n_es_aeat_mod303-18.0.1.0.4.dist-info/RECORD
